django_throttling
tests
